smartschool/__init__.py
smartschool/_dev_tracing.py
smartschool/_xml_interface.py
smartschool/agenda.py
smartschool/common.py
smartschool/courses.py
smartschool/courses.pyi
smartschool/credentials.py
smartschool/exceptions.py
smartschool/future_tasks.py
smartschool/messages.py
smartschool/objects.py
smartschool/periods.py
smartschool/planner.py
smartschool/reports.py
smartschool/reports.pyi
smartschool/results.py
smartschool/results.pyi
smartschool/session.py
smartschool/student_support.py
smartschool-0.7.3.data/scripts/smartschool_report_on_results
smartschool-0.7.3.data/scripts/smartschool_report_on_future_tasks
smartschool-0.7.3.data/scripts/smartschool_report_on_planned_tasks
smartschool-0.7.3.data/scripts/smartschool_browse_docs
smartschool-0.7.3.data/scripts/smartschool_download_all_documents
smartschool-0.7.3.dist-info/METADATA
smartschool-0.7.3.dist-info/WHEEL
smartschool-0.7.3.dist-info/licenses/LICENSE
smartschool-0.7.3.dist-info/RECORD
