Metadata-Version: 2.4
Name: smartschool
Version: 0.7.3
Summary: Unofficial API interface to the smartschool system.
License: GPL-3.0
License-File: LICENSE
Author: Steven Van Ingelgem
Author-email: steven@vaningelgem.be
Requires-Python: >=3.11,<4.0
Classifier: License :: OSI Approved :: GNU General Public License v3 (GPLv3)
Classifier: Programming Language :: Python :: 3
Classifier: Programming Language :: Python :: 3.11
Classifier: Programming Language :: Python :: 3.12
Classifier: Programming Language :: Python :: 3.13
Classifier: Programming Language :: Python :: 3.14
Provides-Extra: mfa
Requires-Dist: bs4
Requires-Dist: logprise
Requires-Dist: pydantic
Requires-Dist: pyotp (>=2.9.0,<3.0.0) ; extra == "mfa"
Requires-Dist: pyyaml
Requires-Dist: requests
Project-URL: Changelog, https://github.com/svaningelgem/smartschool/blob/master/CHANGELOG.md
Project-URL: Homepage, https://github.com/svaningelgem/smartschool
Project-URL: License, https://github.com/svaningelgem/smartschool/blob/master/LICENSE
Project-URL: Source Code, https://github.com/svaningelgem/smartschool
